arraystream-0.1.0.dist-info/METADATA
arraystream-0.1.0.dist-info/WHEEL
arraystream-0.1.0.dist-info/licenses/LICENSE
arraystream/__init__.py
arraystream/_arraystream.cpython-38-darwin.so
arraystream/_core.py
arraystream/boolean.py
arraystream/grouping.py
arraystream/numeric.py
arraystream/structural.py
arraystream-0.1.0.dist-info/RECORD
