Metadata-Version: 2.4
Name: arraystream
Version: 0.1.0
Classifier: Development Status :: 3 - Alpha
Classifier: Intended Audience :: Developers
Classifier: License :: OSI Approved :: MIT License
Classifier: Programming Language :: Python :: 3
Classifier: Programming Language :: Python :: 3.8
Classifier: Programming Language :: Python :: 3.9
Classifier: Programming Language :: Python :: 3.10
Classifier: Programming Language :: Python :: 3.11
Classifier: Programming Language :: Python :: 3.12
Classifier: Programming Language :: Rust
Classifier: Topic :: Software Development :: Libraries :: Python Modules
Requires-Dist: arrayops ; extra == 'arrayops'
Provides-Extra: arrayops
License-File: LICENSE
Summary: Iterator-style transformations for numeric arrays, similar to itertools but for array.array
Keywords: array,stream,transform,numeric,buffer
Author-email: Odos Matthews <odosmatthews@gmail.com>
License: MIT
Requires-Python: >=3.8
Project-URL: Homepage, https://github.com/eddiethedean/arraystream
Project-URL: Repository, https://github.com/eddiethedean/arraystream
Project-URL: Documentation, https://github.com/eddiethedean/arraystream
